{
    "name" : {
        "first" : "Gigi",
        "last" : "Hadid"
    },
    "imgUrl" : "https://drive.google.com/uc?id=1ljWxBQwvCl8QPxOo_sj3mae-6gwfGlI5",
    "email" : "gigi@buy.com",
    "password" : "gigi123",
    "createdAt" : 14342546465465465468,
    "isAdmin" : true,
    "bio" : "You all know me :)",
    "msgs" : [ 
        {
            "createdAt" : 151515145687845.0,
            "txt" : "hello",
            "sentBy" : {
                "_id" : "5ecb9aab0c2535f563044b90",
                "name" : {
                    "first" : "Alexi",
                    "last" : "Romanov"
                },
                "imgUrl" : "https://drive.google.com/uc?id=1CRTUFCJAzwxYqZEGigD6v8UPVz7f7kvX"
            }
        }
    ],
    "product" : {
        "title" : "Fashion And Food Makeover",
        "price" : 280.0,
        "city" : {
            "_id" : "5ecac62d860e88985ad95110",
            "name" : "Barcelona",
            "imgUrl" : "https://drive.google.com/uc?id=1hz_gYOI3GXJ9CoDnmns8VhJiRW5Bf-zo"
        },
        "category" : "Cooking Workshop",
        "tags" : [ 
            "Sexy Food", 
            "Chocolate", 
            "Cocktails"
        ],
        "imgUrls" : [ 
            "https://drive.google.com/uc?id=1y9QK2Vp1bNZUSyhZw_VyVUnloOsbpCgU", 
            "https://drive.google.com/uc?id=1hz_gYOI3GXJ9CoDnmns8VhJiRW5Bf-zo", 
            "https://drive.google.com/uc?id=1tNwXd14FZ1js7YzTKb2jbhK-R-OlsEZv", 
            "https://drive.google.com/uc?id=14fpf4iXBXmyhkQ55tC6MLvYLJU1v1Nl0", 
            "https://drive.google.com/uc?id=18lyKCiDnCvmNtRMA5YY1oyRo3Svwtf1s"
        ],
        "description" : "After a long career as a top-model, now I offer you a glimpse at some of my secrets about food, fashion and qulity drinking",
        "reviews" : [ 
            {
                "txt" : "An unbeleivable experince. I wish no one else would ever try it so I can tell I was the only one",
                "rate" : 5.0,
                "createdAt" : 15904444476723.0,
                "byUser" : {
                    "_id" : "5ed3ab41b120d41948b0d236",
                    "name" : {
                        "first" : "Lara",
                        "last" : "Gabrielle"
                    },
                    "imgUrl" : "https://drive.google.com/uc?id=1NwEzQtve4urrAOEUAO9ax-Z5nOkXpjJF"
                }
            }, 
            {
                "txt" : "Absoloutly amazing. What was amazing? EVERYTHING",
                "rate" : 4.0,
                "createdAt" : 15903444246723.0,
                "byUser" : {
                    "_id" : "5ecb9aab0c2535f563044b92",
                    "name" : {
                        "first" : "Dennis",
                        "last" : "Yorkush"
                    },
                    "imgUrl" : "https://drive.google.com/uc?id=10bmSWI859txhEZPS9T5Ho_6d097f2dFG"
                }
            }
        ]
    }
}